{
  "name": "sym_types",
  "library": "SYMPHONY",
  "layer": "layer-3",
  "header": "include/sym_types.h",
  "brief": "Core data structures for SYMPHONY's branch-and-cut\n\nDefines the fundamental data structures used throughout SYMPHONY\nfor representing problems, solutions, tree nodes, and cuts.\n\n**Problem representation:**\n- MIPdesc: Complete MIP in CSC format (matbeg, matind, matval)\n- MIPinfo: Problem statistics (var types, row types, density)\n\n**Tree node structures:**\n- bc_node: B&C tree node with bounds, solution, children\n- node_desc: Node description (basis, cuts, variables)\n- branch_obj: Branching decision (variable, children, bounds)\n- branch_desc: Single branch description (sense, rhs)\n\n**Cut structures:**\n- cut_data: Cut coefficients and metadata\n- row_data: Cut with effectiveness tracking\n- waiting_row: Pending cut with violation info\n\n**Solution structures:**\n- lp_sol: LP solution (sparse xind/xval format)\n- sp_solution: Solution pool entry\n- warm_start_desc: Complete warm start state\n\n**Statistics:**\n- problem_stat: Tree size, depth, diving stats\n- lp_stat_desc: LP calls, cuts generated by type\n- node_times: Timing breakdown per node\n\n**Presolve support:**\n- COLinfo: Column statistics and implications\n- ROWinfo: Row bounds, types, redundancy\n- IMPvar/IMPlist: Variable implication lists",
  "algorithms": [],
  "methods": [],
  "see": [
    "sym_master.h for sym_environment",
    "sym_tm.h for tm_prob"
  ]
}